[
  {
    "name": "default",
    "initCameraPos": [35, 28],
    "mapName": "darwin",
    "maxShipCount": 5,
    "initShips": [
      {
        "name": "duck",
        "pos": [40, 33],
        "rotation": 90,
        "belongPlayer": "humanAlpha"
      },
      {
        "name": "lowa",
        "pos": [38, 34],
        "rotation": 90,
        "belongPlayer": "humanAlpha"
      },
      {
        "name": "montana",
        "pos": [40, 35],
        "rotation": 90,
        "belongPlayer": "humanAlpha"
      },
      {
        "name": "yamato_plus",
        "pos": [38, 36],
        "rotation": 90,
        "belongPlayer": "humanAlpha"
      },
      {
        "name": "kongo",
        "pos": [40, 37],
        "rotation": 90,
        "belongPlayer": "humanAlpha"
      },
      {
        "name": "alaska_plus",
        "pos": [38, 38],
        "rotation": 90,
        "belongPlayer": "humanAlpha"
      },
      {
        "name": "atlanta",
        "pos": [40, 39],
        "rotation": 90,
        "belongPlayer": "humanAlpha"
      },
      {
        "name": "long_beach",
        "pos": [38, 40],
        "rotation": 90,
        "belongPlayer": "humanAlpha"
      },
      {
        "name": "long_beach",
        "pos": [40, 41],
        "rotation": 90,
        "belongPlayer": "humanAlpha"
      },
      {
        "name": "new_orleans",
        "pos": [38, 42],
        "rotation": 90,
        "belongPlayer": "humanAlpha"
      },
      {
        "name": "mogami",
        "pos": [60, 42],
        "rotation": 270,
        "belongPlayer": "computerAlpha"
      },
      {
        "name": "mogami",
        "pos": [40, 43],
        "rotation": 90,
        "belongPlayer": "humanAlpha"
      },
      {
        "name": "kuma",
        "pos": [38, 44],
        "rotation": 90,
        "belongPlayer": "humanAlpha"
      },
      {
        "name": "porter",
        "pos": [40, 45],
        "rotation": 90,
        "belongPlayer": "humanAlpha"
      },
      {
        "name": "asashio",
        "pos": [38, 46],
        "rotation": 90,
        "belongPlayer": "humanAlpha"
      },
      {
        "name": "asashio",
        "pos": [88, 42],
        "rotation": 270,
        "belongPlayer": "computerAlpha"
      },
      {
        "name": "asashio",
        "pos": [86, 47],
        "rotation": 270,
        "belongPlayer": "computerAlpha"
      },
      {
        "name": "asashio",
        "pos": [93, 42],
        "rotation": 270,
        "belongPlayer": "computerAlpha"
      },
      {
        "name": "asashio",
        "pos": [89, 48],
        "rotation": 270,
        "belongPlayer": "computerAlpha"
      },
      {
        "name": "mogami",
        "pos": [86, 45],
        "rotation": 270,
        "belongPlayer": "computerAlpha"
      },
      {
        "name": "mogami",
        "pos": [87, 43],
        "rotation": 270,
        "belongPlayer": "computerAlpha"
      },
      {
        "name": "yamato_plus",
        "pos": [90, 46],
        "rotation": 270,
        "belongPlayer": "computerAlpha"
      },
      {
        "name": "kongo",
        "pos": [92, 44],
        "rotation": 270,
        "belongPlayer": "computerAlpha"
      },
      {
        "name": "kuma",
        "pos": [92, 48],
        "rotation": 270,
        "belongPlayer": "computerAlpha"
      }
    ]
  }
]
